README.md
setup.py
mp_utils/__init__.py
mp_utils/convert.py
mp_utils/features.py
mp_utils/filters.py
mp_utils/io.py
mp_utils/ocr.py
mp_utils/orb.py
mp_utils/transforms.py
mp_utils/utils.py
mp_utils/vis.py
mp_utils.egg-info/PKG-INFO
mp_utils.egg-info/SOURCES.txt
mp_utils.egg-info/dependency_links.txt
mp_utils.egg-info/not-zip-safe
mp_utils.egg-info/requires.txt
mp_utils.egg-info/top_level.txt