Metadata-Version: 1.1
Name: mp-utils
Version: 1.0
Summary: machine perception utility functions
Home-page: UNKNOWN
Author: Kevin Glasson
Author-email: kevinglasson+mp_utils@gmail.com
License: MIT
Platform: UNKNOWN
Classifier: License :: OSI Approved :: MIT License
Classifier: Operating System :: OS Independent
